{"cameraMode":{"drawMode":0,"name":"Shaded","section":"Shading Mode"},"sceneLighting":true,"audioPlay":false,"sceneViewState":{"m_AlwaysRefresh":false,"showFog":true,"showSkybox":true,"showFlares":true,"showImageEffects":true,"showParticleSystems":true,"showVisualEffectGraphs":true,"m_FxEnabled":true},"in2DMode":false,"pivot":{"x":5.581725120544434,"y":4.213974952697754,"z":-26.364809036254884},"rotation":{"x":-0.3223327100276947,"y":0.5075406432151794,"z":-0.2123761922121048,"w":-0.7702938318252564},"size":0.8660253882408142,"orthographic":false}